MANIFEST.in
README.rst
setup.cfg
setup.py
bitcasa/__init__.py
bitcasa/client.py
bitcasa/exception.py
bitcasa/filesystem.py
bitcasa/version.py
bitcasa.egg-info/PKG-INFO
bitcasa.egg-info/SOURCES.txt
bitcasa.egg-info/dependency_links.txt
bitcasa.egg-info/requires.txt
bitcasa.egg-info/top_level.txt
bitcasa/tests/__init__.py
bitcasa/tests/test_client.py
bitcasa/tests/test_files.py
bitcasa/tests/test_folders.py