Metadata-Version: 1.1
Name: bitcasa
Version: 1.0
Summary: This is the Python SDK for the Bitcasa API.
Home-page: http://www.bitcasa.com/
Author: Bitcasa, Inc.
Author-email: api@bitcasa.com
License: MIT
Download-URL: https://github.com/bitcasa/bitcasa-sdk-python/tarball/v1.0
Keywords: bitcasa sdk
Platform: UNKNOWN
Classifier: Development Status :: 5 - Production/Stable
Classifier: Environment :: Web Environment
Classifier: Natural Language :: English
Classifier: Intended Audience :: Developers
Classifier: License :: OSI Approved :: MIT License
Classifier: Programming Language :: Python
Classifier: Programming Language :: Python :: 2.7
Classifier: Programming Language :: Python :: 3
Classifier: Programming Language :: Python :: 3.2
Classifier: Programming Language :: Python :: 3.3
Classifier: Topic :: Utilities
